readline.py
pyreadline3/__init__.py
pyreadline3/error.py
pyreadline3/get_doc.py
pyreadline3/logger.py
pyreadline3/py3k_compat.py
pyreadline3/release.py
pyreadline3/rlmain.py
pyreadline3/unicode_helper.py
pyreadline3/clipboard/__init__.py
pyreadline3/clipboard/ironpython_clipboard.py
pyreadline3/clipboard/no_clipboard.py
pyreadline3/clipboard/win32_clipboard.py
pyreadline3/configuration/pyreadlineconfig.ini
pyreadline3/configuration/startup.py
pyreadline3/console/__init__.py
pyreadline3/console/ansi.py
pyreadline3/console/console.py
pyreadline3/console/console_attributes.py
pyreadline3/console/consolebase.py
pyreadline3/console/event.py
pyreadline3/console/ironpython_console.py
pyreadline3/keysyms/__init__.py
pyreadline3/keysyms/common.py
pyreadline3/keysyms/ironpython_keysyms.py
pyreadline3/keysyms/keysyms.py
pyreadline3/keysyms/winconstants.py
pyreadline3/lineeditor/__init__.py
pyreadline3/lineeditor/history.py
pyreadline3/lineeditor/lineobj.py
pyreadline3/lineeditor/wordmatcher.py
pyreadline3/modes/__init__.py
pyreadline3/modes/basemode.py
pyreadline3/modes/emacs.py
pyreadline3/modes/notemacs.py
pyreadline3/modes/vi.py
pyreadline3-3.5.3.dist-info/LICENSE.md
pyreadline3-3.5.3.dist-info/METADATA
pyreadline3-3.5.3.dist-info/WHEEL
pyreadline3-3.5.3.dist-info/top_level.txt
pyreadline3-3.5.3.dist-info/RECORD
