Metadata-Version: 2.1
Name: pyreadline3
Version: 3.5.3
Summary: A python implementation of GNU readline.
Author-email: Bassem Girgis <brgirgis@gmail.com>, Jorgen Stenarson <jorgen.stenarson@kroywen.se>, Gary Bishop <unknwon@unknown.com>, Jack Trainor <unknwon@unknown.com>
Maintainer-email: Bassem Girgis <brgirgis@gmail.com>
License: BSD
Project-URL: Homepage, https://github.com/pyreadline3/pyreadline3
Project-URL: Documentation, https://github.com/pyreadline3/pyreadline3
Project-URL: Repository, https://github.com/pyreadline3/pyreadline3.git
Project-URL: Issues, https://github.com/pyreadline3/pyreadline3/issues
Project-URL: Changelog, https://github.com/pyreadline3/pyreadline3/blob/master/doc/ChangeLog
Keywords: readline,pyreadline,pyreadline3
Classifier: Development Status :: 5 - Production/Stable
Classifier: Environment :: Console
Classifier: Operating System :: Microsoft :: Windows
Classifier: License :: OSI Approved :: BSD License
Classifier: Programming Language :: Python :: 3.8
Classifier: Programming Language :: Python :: 3.9
Classifier: Programming Language :: Python :: 3.10
Classifier: Programming Language :: Python :: 3.11
Classifier: Programming Language :: Python :: 3.12
Requires-Python: >=3.8
License-File: LICENSE.md
Provides-Extra: dev
Requires-Dist: build ; extra == 'dev'
Requires-Dist: flake8 ; extra == 'dev'
Requires-Dist: mypy ; extra == 'dev'
Requires-Dist: pytest ; extra == 'dev'
Requires-Dist: twine ; extra == 'dev'
